{
	"classFluff": [
		{
			"name": "游荡者",
			"ENG_name": "Rogue",
			"source": "PHB",
			"entries": [
				{
					"name": "游荡者",
					"ENG_name": "Rogue",
					"type": "section",
					"entries": [
						"示意同伴们等待，一个半身人悄悄穿过地牢大厅。她将耳朵贴在门上，然后拿出一套工具，在眨眼间撬开了锁。然后她消失在阴影中，而她的战士朋友走上前去踢开门。",
						"一个人类潜伏在小巷的阴影中，而他的同伙正在为伏击做准备。当他们的目标\u2014\u2014一个臭名昭著的奴隶贩子\u2014\u2014经过小巷时，同伙大声呼喊，奴隶贩子前来调查，刺客的刀刃在他发出声音之前就割断了他的喉咙。",
						"一个侏儒女孩压抑着笑声，用魔法将钥匙圈从守卫的腰带上轻轻提起。转眼间，钥匙已经在她手中，牢门被打开，她和她的同伴们自由地逃走了。",
						"盗贼依靠技巧、隐秘和敌人的弱点在任何情况下取得优势。他们有一种找到几乎任何问题解决方案的天赋，展现出一种机智和多样性，这是任何成功的冒险队伍的基石。",
						{
							"type": "entries",
							"name": "技能和精准",
							"ENG_name": "Skill and Precision",
							"entries": [
								"盗贼们投入与完善战斗能力同样多的努力来掌握各种技能，这使他们拥有其他角色难以匹敌的广泛专长。许多盗贼专注于潜行和欺骗，而其他人则精炼那些在地下城环境中帮助他们的技能，如攀爬、发现和解除陷阱以及开锁。",
								"在战斗中，流氓更倾向于使用狡猾而非蛮力。流氓宁愿进行一次精确的打击，将其放置在能最大程度伤害目标的地方，而不是通过一连串的攻击来耗尽对手。流氓具有几乎超自然的避免危险的技巧，一些流氓还学会了魔法技巧来补充他们的其他能力。"
							]
						},
						{
							"type": "entries",
							"name": "阴暗生活",
							"ENG_name": "A Shady Living",
							"entries": [
								"每个城镇和城市都有它自己的盗贼。他们中的大多数人符合这个职业最坏的刻板印象，以窃贼、刺客、扒手和诈骗艺术家的身份谋生。通常，这些恶棍被组织进盗贼公会或犯罪家族。许多盗贼独立行动，但即使他们有时也会招募学徒来帮助他们进行诈骗和抢劫。一些盗贼以锁匠、调查员或灭害者的身份诚实谋生，在一个由老鼠和狼人老鼠出没的下水道的世界中，这可能是一份危险的工作。",
								"作为冒险者，盗贼站在法律的两边。有些是决定在宝藏中寻求财富的硬核罪犯，而另一些则是为了逃避法律而选择冒险生活。有些人为了潜入古代遗迹和隐藏的墓穴寻找宝藏，已经学会了并完善了他们的技能。"
							]
						},
						{
							"type": "entries",
							"name": "创建游荡者",
							"ENG_name": "Creating a Rogue",
							"entries": [
								"当你创建你的盗贼角色时，考虑角色与法律的关系。你是否有过犯罪的历史\u2014\u2014或者现在？你是否在逃避法律或一个愤怒的盗贼公会大师的追捕？还是你离开了你的公会，去寻找更大的风险和更大的回报？是贪婪驱使你在冒险中，还是其他的欲望或理想？",
								"是什么触发因素让你远离了之前的生活？是不是一次大骗局或抢劫出了大错，让你重新评估你的职业？也许你很幸运，一次成功的抢劫给了你逃离你生活中贫困所需的金钱。是不是流浪的欲望最终召唤你离开了你的家？也许你突然发现自己与家人或导师断绝了联系，你必须找到新的支持方式。或者也许你交了新朋友\u2014\u2014你的冒险团队的另一个成员\u2014\u2014他向你展示了赚取生活和利用你特殊才能的新可能性。",
								{
									"type": "entries",
									"name": "快速建卡",
									"ENG_name": "Quick Build",
									"entries": [
										"你可以按照这些建议快速创建一个盗贼角色。首先，敏捷应该是你最高的属性值。如果你想要擅长调查或计划选择奥术诡术师原型，那么智力应该是你第二高的属性值。如果你打算强调欺骗和社交互动，选择魅力。其次，选择{@background 骗子}背景。"
									]
								}
							]
						}
					],
					"page": 94,
					"source": "PHB"
				},
				{
					"type": "section",
					"entries": [
						{
							"type": "quote",
							"entries": [
								"人们忘记了，冒险进入一个尘封的墓穴的真正目的是为了带回那里隐藏的宝藏。战斗是愚蠢的。死人无法享用他们的财富。"
							],
							"by": "巴纳巴斯·刀刃切割者"
						},
						"当蛮力无法完成任务，或者魔法不可用或不适当时，流氓便脱颖而出。流氓的技能与潜行、欺骗和诡计有关，他们能够以其他角色难以模仿的方式陷入和摆脱麻烦。",
						"一些转而成为冒险者的盗贼是前罪犯，他们决定躲避怪物比一直逃避法律要好。另一些是职业杀手，他们在合同间隙寻找他们才能的有利可图的应用。还有一些人仅仅是喜欢克服任何挡在他们路上的挑战所带来的刺激。",
						"在冒险中，一个盗贼可能会表现出外表谨慎的态度\u2014\u2014很少有盗贼喜欢战斗\u2014\u2014同时对战利品有着极度的渴望。大多数时候，在盗贼的心中，拿起武器对抗一个生物并不是为了杀死这个生物，而是为了成为它宝藏的新主人。",
						"以下部分探讨了作为一个盗贼角色的一些方面，你可以用它们来增加你角色的深度。",
						{
							"type": "entries",
							"name": "罪恶的快感",
							"ENG_name": "Guilty Pleasures",
							"entries": [
								"大多数盗贼的行为都围绕着获取财宝和阻止他人做同样的事情。除了一种冲动使他们的思维变得模糊，很少有东西会阻碍他们实现这些目标\u2014\u2014这种冲动必须得到满足，即使这样做是有风险的。",
								"一个盗贼的罪恶乐趣可能是获取一件实物，体验某件事情，或者在特定时候以某种方式行事。例如，一个盗贼可能无法抗拒任何由银制成的战利品，即使这些战利品挂在城堡守卫的脖子上。另一个盗贼可能无法在城市中度过一天而不偷一两个钱包，只是为了保持练习。",
								"当你的盗贼角色面临机会时，有哪些诱惑是他们无法抗拒的，即使屈服于这些诱惑可能会给你和你的同伴带来麻烦？",
								{
									"type": "table",
									"caption": "罪恶的快感",
									"colLabels": [
										"{@dice d6}",
										"愉悦"
									],
									"colStyles": [
										"col-1 text-center",
										"col-11"
									],
									"rows": [
										[
											{
												"type": "cell",
												"roll": {
													"exact": 1
												}
											},
											"美丽面庞上的微笑"
										],
										[
											{
												"type": "cell",
												"roll": {
													"exact": 2
												}
											},
											"你手指上的新戒指"
										],
										[
											{
												"type": "cell",
												"roll": {
													"exact": 3
												}
											},
											"削弱某人自负的机会"
										],
										[
											{
												"type": "cell",
												"roll": {
													"exact": 4
												}
											},
											"最优质的食品和饮料"
										],
										[
											{
												"type": "cell",
												"roll": {
													"exact": 5
												}
											},
											"增加你收藏的异国硬币"
										],
										[
											{
												"type": "cell",
												"roll": {
													"exact": 6
												}
											},
											"你曾经服务过的海盗船长；你称之为前进，船长称之为叛变"
										]
									]
								}
							]
						},
						{
							"type": "entries",
							"name": "对手",
							"ENG_name": "Adversaries",
							"entries": [
								"自然地，那些执行法律的人难免会遇到那些违反法律的人，而且很少有盗贼没有至少一张通缉令。除此之外，由于他们职业的性质，盗贼经常与犯罪分子接触，无论是出于选择还是出于必要。其中一些人可能是对手，他们可能比城市警卫队的普通成员更难对付。",
								"如果你的角色背景故事中还没有包含这类人物，你可以与你的地下城主合作，想出一个为什么敌人会出现在你的生活中的理由。也许你已经被某个想要利用你进行不法目的的人观察了一段时间，并且现在才让你知道。这样的事件可以成为即将到来的冒险的基础。",
								"你的盗贼角色是否有一个对手，而这个对手恰好也是一个罪犯？如果是，这种关系是如何影响你的生活？",
								{
									"type": "table",
									"caption": "对手",
									"colLabels": [
										"{@dice d6}",
										"对手"
									],
									"colStyles": [
										"col-1 text-center",
										"col-11"
									],
									"rows": [
										[
											{
												"type": "cell",
												"roll": {
													"exact": 1
												}
											},
											"你曾经服务过的海盗船长；你们所谓的前进，船长称之为叛变"
										],
										[
											{
												"type": "cell",
												"roll": {
													"exact": 2
												}
											},
											"一个你无意中提供错误信息的高级间谍，这导致了错误目标的暗杀"
										],
										[
											{
												"type": "cell",
												"roll": {
													"exact": 3
												}
											},
											"当地盗贼公会的首领，他希望你加入该组织或离开城镇"
										],
										[
											{
												"type": "cell",
												"roll": {
													"exact": 4
												}
											},
											"一个使用非法手段获取杰作的艺术收藏家"
										],
										[
											{
												"type": "cell",
												"roll": {
													"exact": 5
												}
											},
											"一个走私者让你免于被捕，但在此过程中失去了一批价值连城的货物。现在你欠那个人一个同样有价值的人情。"
										],
										[
											{
												"type": "cell",
												"roll": {
													"exact": 6
												}
											},
											"一个非法地下格斗场的老板，你曾经在那里下注"
										]
									]
								}
							]
						},
						{
							"type": "entries",
							"name": "恩人",
							"ENG_name": "Benefactor",
							"entries": [
								"很少有盗贼能在人生中走得很远而不需要别人的帮助，这意味着之后欠下了那位恩人一笔巨大的债务。",
								"如果你的角色背景故事中还没有包含这样一个人，你可以与你的DM合作，确定为什么一个赞助者会出现在你的生活中。也许因为你的赞助者为你做了一些事情，而你没有意识到是谁负责，现在这个人刚刚被你知道。在过去，无论当时你是否知道，谁帮助了你，你又欠那个人什么作为回报？",
								{
									"type": "table",
									"caption": "赞助者",
									"colLabels": [
										"{@dice d6}",
										"恩人"
									],
									"colStyles": [
										"col-1 text-center",
										"col-11"
									],
									"rows": [
										[
											{
												"type": "cell",
												"roll": {
													"exact": 1
												}
											},
											"一个走私者帮你避免了被捕，但在这个过程中失去了一批价值连城的货物。现在你欠那个人一个同样有价值的人情。"
										],
										[
											{
												"type": "cell",
												"roll": {
													"exact": 2
												}
											},
											"乞丐王多次将你从追捕者手中隐藏起来，作为未来回报的交换。"
										],
										[
											{
												"type": "cell",
												"roll": {
													"exact": 3
												}
											},
											"一位法官曾为了换取有关一个强大黑帮老大的信息而让你免于入狱。"
										],
										[
											{
												"type": "cell",
												"roll": {
													"exact": 4
												}
											},
											"你的父母用他们的积蓄帮你摆脱了年轻时的麻烦，现在他们一贫如洗。"
										],
										[
											{
												"type": "cell",
												"roll": {
													"exact": 5
												}
											},
											"一条龙在有机会时没有吃掉你，作为回报，你承诺为它留下一些珍贵的宝藏。"
										],
										[
											{
												"type": "cell",
												"roll": {
													"exact": 6
												}
											},
											"一位德鲁伊曾经帮你摆脱了困境；现在你看到的任何随机动物都可能是那个恩人，也许来要求回报。"
										]
									]
								}
							]
						}
					],
					"page": 44,
					"source": "XGE"
				}
			],
			"images": [
				{
					"type": "image",
					"href": {
						"type": "internal",
						"path": "classes/PHB/Rogue.webp"
					}
				}
			]
		},
		{
			"name": "游荡者",
			"ENG_name": "Rogue",
			"source": "XPHB",
			"entries": [
				{
					"type": "section",
					"name": "游荡者",
					"ENG_name": "Rogue",
					"source": "XPHB",
					"page": 128,
					"entries": [
						"盗贼依靠狡猾、潜行和敌人的弱点来在任何情况下占据优势。他们擅长找到几乎任何问题的解决方案。一些人甚至学会了魔法技巧来补充他们的其他能力。许多盗贼专注于潜行和欺骗，而其他人则磨练在地下城环境中帮助他们的技能，例如攀爬、发现和解除陷阱以及开锁。",
						"在战斗中，盗贼优先考虑巧妙的打击而不是蛮力。他们宁愿进行一次精确的打击，也不愿用一连串的打击来消耗对手。",
						"有些盗贼起初是罪犯，而其他人则利用他们的狡猾来打击犯罪。无论盗贼与法律的关系如何，普通的罪犯或执法人员都无法与最伟大的盗贼的微妙才华相匹敌。"
					]
				}
			],
			"images": [
				{
					"type": "image",
					"href": {
						"type": "internal",
						"path": "classes/XPHB/Rogue.webp"
					},
					"credit": "Aurore Folny"
				},
				{
					"type": "image",
					"href": {
						"type": "internal",
						"path": "classes/XPHB/099-04-014.cunning-rogue.webp"
					},
					"credit": "Bryan Sola"
				},
				{
					"type": "image",
					"href": {
						"type": "internal",
						"path": "classes/XPHB/101-04-016.rogue-v-dragon.webp"
					},
					"credit": "Billy Christian"
				},
				{
					"type": "image",
					"href": {
						"type": "internal",
						"path": "classes/XPHB/104-04-019.sneak-attack.webp"
					},
					"credit": "伊文·方"
				}
			]
		}
	],
	"subclassFluff": [
		{
			"name": "鬼魅",
			"ENG_name": "Phantom",
			"shortName": "鬼魅",
			"source": "TCE",
			"className": "游荡者",
			"classSource": "PHB",
			"images": [
				{
					"type": "image",
					"href": {
						"type": "internal",
						"path": "classes/TCE/Phantom Rogue.webp"
					}
				}
			]
		},
		{
			"name": "魂刃",
			"ENG_name": "Soulknife",
			"shortName": "魂刃",
			"source": "TCE",
			"className": "游荡者",
			"classSource": "PHB",
			"images": [
				{
					"type": "image",
					"href": {
						"type": "internal",
						"path": "classes/TCE/Soulknife Rogue.webp"
					}
				}
			]
		},
		{
			"name": "诡术师",
			"ENG_name": "Arcane Trickster",
			"shortName": "诡术师",
			"source": "XPHB",
			"className": "游荡者",
			"classSource": "XPHB",
			"images": [
				{
					"type": "image",
					"href": {
						"type": "internal",
						"path": "classes/XPHB/Arcane Trickster Rogue.webp"
					},
					"credit": "纳撒尼尔·希玛万"
				}
			]
		},
		{
			"name": "刺客",
			"ENG_name": "Assassin",
			"shortName": "刺客",
			"source": "XPHB",
			"className": "游荡者",
			"classSource": "XPHB",
			"images": [
				{
					"type": "image",
					"href": {
						"type": "internal",
						"path": "classes/XPHB/Assassin Rogue.webp"
					},
					"credit": "Ignatius Budi"
				}
			]
		},
		{
			"name": "魂刃",
			"ENG_name": "Soulknife",
			"shortName": "魂刃",
			"source": "XPHB",
			"className": "游荡者",
			"classSource": "XPHB",
			"images": [
				{
					"type": "image",
					"href": {
						"type": "internal",
						"path": "classes/XPHB/Soulknife Rogue.webp"
					},
					"credit": "Yuhong Ding"
				}
			]
		},
		{
			"name": "盗贼",
			"ENG_name": "Thief",
			"shortName": "盗贼",
			"source": "XPHB",
			"className": "游荡者",
			"classSource": "XPHB",
			"images": [
				{
					"type": "image",
					"href": {
						"type": "internal",
						"path": "classes/XPHB/Thief Rogue.webp"
					},
					"credit": "乔迪·缪尔"
				}
			]
		}
	]
}
