{
	"spell": [
		{
			"name": "空气泡泡",
			"ENG_name": "Air Bubble",
			"source": "AAG",
			"page": 22,
			"level": 2,
			"school": "C",
			"time": [
				{
					"number": 1,
					"unit": "动作"
				}
			],
			"range": {
				"type": "point",
				"distance": {
					"type": "feet",
					"amount": 60
				}
			},
			"components": {
				"s": true
			},
			"duration": [
				{
					"type": "timed",
					"duration": {
						"type": "hour",
						"amount": 24
					}
				}
			],
			"entries": [
				"你围绕你能看到的范围内的一个愿意的生物的头部创造了一个幽灵般的光球。光球内充满了新鲜空气，直到法术结束。如果这个生物有多个头部，空气球只出现在其中一个头部周围（这足以避免窒息，假设所有头部共享同一个呼吸系统）。"
			],
			"entriesHigherLevel": [
				{
					"type": "entries",
					"name": "升环施法效应",
					"ENG_name": "At Higher Levels",
					"entries": [
						"当你使用3级或更高等级的法术位施放这个法术时，每超过2级，你可以额外创造两个新鲜的空气球。"
					]
				}
			],
			"miscTags": [
				"SGT"
			],
			"hasFluffImages": true
		},
		{
			"name": "创造法驱魔舵",
			"ENG_name": "Create Spelljamming Helm",
			"source": "AAG",
			"page": 22,
			"level": 5,
			"school": "T",
			"time": [
				{
					"number": 1,
					"unit": "动作"
				}
			],
			"range": {
				"type": "point",
				"distance": {
					"type": "touch"
				}
			},
			"components": {
				"v": true,
				"s": true,
				"m": {
					"text": "一根至少价值5,000金币的水晶棒，法术会消耗它",
					"cost": 500000,
					"consume": true
				}
			},
			"duration": [
				{
					"type": "instant"
				}
			],
			"entries": [
				"手持用于施放法术的法杖，你触摸一个未被占用的大型或更小的椅子。法杖消失，椅子被转化成一个{@item 法驱魔舵|AAG}。"
			]
		}
	]
}
