{
	"conditionFluff": [
		{
			"name": "目盲",
			"ENG_name": "Blinded",
			"source": "PHB",
			"images": [
				{
					"type": "image",
					"href": {
						"type": "internal",
						"path": "conditionsdiseases/PHB/blinded.webp"
					}
				}
			]
		},
		{
			"name": "魅惑",
			"ENG_name": "Charmed",
			"source": "PHB",
			"images": [
				{
					"type": "image",
					"href": {
						"type": "internal",
						"path": "conditionsdiseases/PHB/charmed.webp"
					}
				}
			]
		},
		{
			"name": "耳聋",
			"ENG_name": "Deafened",
			"source": "PHB",
			"images": [
				{
					"type": "image",
					"href": {
						"type": "internal",
						"path": "conditionsdiseases/PHB/deafened.webp"
					}
				}
			]
		},
		{
			"name": "恐慌",
			"ENG_name": "Frightened",
			"source": "PHB",
			"images": [
				{
					"type": "image",
					"href": {
						"type": "internal",
						"path": "conditionsdiseases/PHB/frightened.webp"
					}
				}
			]
		},
		{
			"name": "擒抱",
			"ENG_name": "Grappled",
			"source": "PHB",
			"images": [
				{
					"type": "image",
					"href": {
						"type": "internal",
						"path": "conditionsdiseases/PHB/grappled.webp"
					}
				}
			]
		},
		{
			"name": "隐形",
			"ENG_name": "Invisible",
			"source": "PHB",
			"images": [
				{
					"type": "image",
					"href": {
						"type": "internal",
						"path": "conditionsdiseases/PHB/invisible.webp"
					}
				}
			]
		},
		{
			"name": "麻痹",
			"ENG_name": "Paralyzed",
			"source": "PHB",
			"images": [
				{
					"type": "image",
					"href": {
						"type": "internal",
						"path": "conditionsdiseases/PHB/paralyzed.webp"
					}
				}
			]
		},
		{
			"name": "石化",
			"ENG_name": "Petrified",
			"source": "PHB",
			"images": [
				{
					"type": "image",
					"href": {
						"type": "internal",
						"path": "conditionsdiseases/PHB/petrified.webp"
					}
				}
			]
		},
		{
			"name": "中毒",
			"ENG_name": "Poisoned",
			"source": "PHB",
			"images": [
				{
					"type": "image",
					"href": {
						"type": "internal",
						"path": "conditionsdiseases/PHB/poisoned.webp"
					}
				}
			]
		},
		{
			"name": "倒地",
			"ENG_name": "Prone",
			"source": "PHB",
			"images": [
				{
					"type": "image",
					"href": {
						"type": "internal",
						"path": "conditionsdiseases/PHB/prone.webp"
					}
				}
			]
		},
		{
			"name": "束缚",
			"ENG_name": "Restrained",
			"source": "PHB",
			"images": [
				{
					"type": "image",
					"href": {
						"type": "internal",
						"path": "conditionsdiseases/PHB/restrained.webp"
					}
				}
			]
		},
		{
			"name": "震慑",
			"ENG_name": "Stunned",
			"source": "PHB",
			"images": [
				{
					"type": "image",
					"href": {
						"type": "internal",
						"path": "conditionsdiseases/PHB/stunned.webp"
					}
				}
			]
		},
		{
			"name": "昏迷",
			"ENG_name": "Unconscious",
			"source": "PHB",
			"images": [
				{
					"type": "image",
					"href": {
						"type": "internal",
						"path": "conditionsdiseases/PHB/unconscious.webp"
					}
				}
			]
		}
	]
}
